IP/RISCV_ADAS_Controller/src/security_unit.v
`timescale 1ns / 1ps
/*
 * Module: security_unit
 * Description: Physical interlock FSM. Prevents the AI from applying the brakes
 * unless a physical switch (sw_brake_arm) is armed AND the system is fault-free.
 */

module security_unit (
    input  wire clk,
    input  wire rst_n,
    
    input  wire sw_brake_arm,       // Physical switch to allow braking
    input  wire emergency_trigger,  // From sensor_fusion
    input  wire system_fault,       // From safety_unit
    
    output reg  brake_authorized    // Final output to the physical brake actuator (or LED5)
);

    // FSM States
    localparam STATE_LOCKED     = 2'd0;
    localparam STATE_VERIFY     = 2'd1;
    localparam STATE_UNLOCKED   = 2'd2;
    localparam STATE_FAULT      = 2'd3;

    reg [1:0] current_state, next_state;

    // FSM State Register
    always @(posedge clk or negedge rst_n) begin
        if (!rst_n) begin
            current_state <= STATE_LOCKED;
        end else begin
            if (system_fault)
                current_state <= STATE_FAULT;
            else
                current_state <= next_state;
        end
    end

    // FSM Next State & Output Logic
    always @(*) begin
        // Default assignments
        next_state = current_state;
        brake_authorized = 1'b0;

        case (current_state)
            STATE_LOCKED: begin
                if (sw_brake_arm)
                    next_state = STATE_VERIFY;
            end
            
            STATE_VERIFY: begin
                if (!sw_brake_arm)
                    next_state = STATE_LOCKED;
                else if (emergency_trigger)
                    next_state = STATE_UNLOCKED;
            end
            
            STATE_UNLOCKED: begin
                brake_authorized = 1'b1; // BRAKES APPLIED
                if (!sw_brake_arm)
                    next_state = STATE_LOCKED; // Physical disarm overrides everything
                else if (!emergency_trigger)
                    next_state = STATE_VERIFY;
            end
            
            STATE_FAULT: begin
                // In a fault state, we disable brakes (safe-state)
                brake_authorized = 1'b0; 
                // Only a hard reset can exit STATE_FAULT (due to safety_unit latching)
            end
            
            default: next_state = STATE_LOCKED;
        endcase
    end

endmodule

IP/RISCV_ADAS_Controller/src/safety_unit.v
`timescale 1ns / 1ps
/*
 * Module: safety_unit
 * Description: ISO-26262 Hardware Watchdog Timer (WDT).
 * The RISC-V core must toggle the wdt_pet signal periodically.
 * If the WDT overflows, a system_fault is latched.
 */

module safety_unit #(
    // 125 MHz clock. 125,000,000 ticks = 1 second.
    // 12,500,000 ticks = 100 ms timeout.
    parameter TIMEOUT_CYCLES = 32'd12500000 
)(
    input  wire clk,
    input  wire rst_n,          // Hardware reset
    input  wire wdt_pet,        // Toggle from RISC-V to reset timer
    
    output reg  system_fault    // Goes high if WDT expires
);

    reg [31:0] wdt_counter;
    reg last_wdt_pet;

    always @(posedge clk or negedge rst_n) begin
        if (!rst_n) begin
            wdt_counter <= 32'd0;
            system_fault <= 1'b0;
            last_wdt_pet <= 1'b0;
        end else begin
            last_wdt_pet <= wdt_pet;
            
            if (system_fault == 1'b0) begin
                // Check for pet (edge detection)
                if (wdt_pet != last_wdt_pet) begin
                    wdt_counter <= 32'd0; // Reset timer
                end else begin
                    wdt_counter <= wdt_counter + 1;
                    if (wdt_counter >= TIMEOUT_CYCLES) begin
                        system_fault <= 1'b1; // Trigger fault!
                    end
                end
            end
            // Note: If system_fault is 1, it stays 1 until hard rst_n (Latching fault)
        end
    end

endmodule

IP/RISCV_ADAS_Controller/src/sensor_fusion.v
`timescale 1ns / 1ps
/*
 * Module: sensor_fusion
 * Description: ADAS Sensor Fusion module inspired by ISO-26262 principles.
 * It combines inputs from the NPU (via RISC-V) and assigns severity scores.
 * Uses a sticky latch for emergency states to prevent glitches from clearing faults.
 */

module sensor_fusion (
    input  wire clk,
    input  wire rst_n,          // Active-low reset (from BTN3)
    
    // NPU / RISC-V Inputs
    input  wire ped_detected,
    input  wire obs_detected,
    input  wire lane_detected,
    input  wire sign_overspeed,
    
    // Switch / Severity Config Inputs
    input  wire [1:0] lane_severity, // 00=safe, 11=critical
    input  wire ped_en,
    input  wire obs_en,
    input  wire lane_en,
    
    // Outputs
    output reg  emergency_trigger,
    output reg  warning_ped,
    output reg  warning_lane,
    output reg  warning_sign
);

    // Hazard Score Calculation
    wire [2:0] hazard_score;
    assign hazard_score = ((ped_detected & ped_en) ? 3'd4 : 3'd0) + 
                          ((obs_detected & obs_en) ? 3'd3 : 3'd0) + 
                          ((lane_detected & lane_en) ? {1'b0, lane_severity} : 3'd0) +
                          (sign_overspeed ? 3'd1 : 3'd0);

    // Synchronous Logic with Sticky Emergency State
    always @(posedge clk or negedge rst_n) begin
        if (!rst_n) begin
            emergency_trigger <= 1'b0;
            warning_ped <= 1'b0;
            warning_lane <= 1'b0;
            warning_sign <= 1'b0;
        end else begin
            // Warnings are continuous and reflect current state
            warning_ped  <= ped_detected & ped_en;
            warning_lane <= lane_detected & lane_en;
            warning_sign <= sign_overspeed;
            
            // EMERGENCY TRIGGER is a Sticky Latch.
            // Once the hazard score exceeds 3, the emergency state locks HIGH.
            // It can ONLY be cleared by a hard physical reset (rst_n).
            if (hazard_score >= 3'd3) begin
                emergency_trigger <= 1'b1;
            end
            // Note: No 'else' condition here for emergency_trigger to make it sticky!
        end
    end

endmodule

verification/tb/tb_adas_features.sv
`timescale 1ns / 1ps

module tb_adas_features();

    reg clk;
    reg rst_n;

    // Sensor Fusion Inputs
    reg ped_detected;
    reg obs_detected;
    reg lane_detected;
    reg sign_overspeed;
    reg [1:0] lane_severity;
    reg ped_en;
    reg obs_en;
    reg lane_en;

    // Safety Unit Inputs
    reg wdt_pet;
    reg stop_petting;

    // Security Unit Inputs
    reg sw_brake_arm;

    // Outputs
    wire emergency_trigger;
    wire warning_ped;
    wire warning_lane;
    wire warning_sign;
    wire system_fault;
    wire brake_authorized;

    // Instantiations
    sensor_fusion u_fusion (
        .clk(clk),
        .rst_n(rst_n),
        .ped_detected(ped_detected),
        .obs_detected(obs_detected),
        .lane_detected(lane_detected),
        .sign_overspeed(sign_overspeed),
        .lane_severity(lane_severity),
        .ped_en(ped_en),
        .obs_en(obs_en),
        .lane_en(lane_en),
        .emergency_trigger(emergency_trigger),
        .warning_ped(warning_ped),
        .warning_lane(warning_lane),
        .warning_sign(warning_sign)
    );

    safety_unit #(
        .TIMEOUT_CYCLES(50) // Small timeout for fast simulation
    ) u_safety (
        .clk(clk),
        .rst_n(rst_n),
        .wdt_pet(wdt_pet),
        .system_fault(system_fault)
    );

    security_unit u_security (
        .clk(clk),
        .rst_n(rst_n),
        .sw_brake_arm(sw_brake_arm),
        .emergency_trigger(emergency_trigger),
        .system_fault(system_fault),
        .brake_authorized(brake_authorized)
    );

    // Clock gen
    always #4 clk = ~clk; // 125 MHz

    initial begin
        // Setup GTKWave / XSIM tracing
        $dumpfile("adas_features.vcd");
        $dumpvars(0, tb_adas_features);
        
        // Initialize
        clk = 0;
        rst_n = 0;
        ped_detected = 0;
        obs_detected = 0;
        lane_detected = 0;
        sign_overspeed = 0;
        lane_severity = 0;
        ped_en = 1;
        obs_en = 1;
        lane_en = 1;
        wdt_pet = 0;
        sw_brake_arm = 0;
        stop_petting = 0;

        repeat(3) @(negedge clk);
        rst_n = 1;

        // ----------------------------------------------------
        // TEST 1: Pedestrian Detection & Normal Brake
        // ----------------------------------------------------
        $display("TEST 1: Pedestrian Detection");
        repeat(3) @(negedge clk);
        sw_brake_arm = 1; // Driver arms the system
        repeat(3) @(negedge clk);
        ped_detected = 1; // NPU sees pedestrian
        repeat(5) @(negedge clk);
        if (warning_ped && brake_authorized) $display("PASS: Brake applied for pedestrian.");
        else $display("FAIL: Brake not applied! (Due to sensor_fusion.v bug: hazard_score < 3)");
        ped_detected = 0;

        // ----------------------------------------------------
        // TEST 2: Security Interlock (Brake Disarmed)
        // ----------------------------------------------------
        $display("TEST 2: Disarmed System");
        sw_brake_arm = 0; // Driver disarms system
        // We will force a hazard score of 3 using lane severity
        @(negedge clk);
        lane_detected = 1;
        lane_severity = 2'b11; 
        repeat(5) @(negedge clk);
        if (!brake_authorized) $display("PASS: Brake was correctly blocked by security unit.");
        else $display("FAIL: Brake bypassed security!");
        lane_detected = 0;
        lane_severity = 0;
        
        // Because emergency_trigger is sticky, we need a hard reset to clear it for the next tests
        rst_n = 0;
        repeat(3) @(negedge clk);
        rst_n = 1;

        // ----------------------------------------------------
        // TEST 3: Lane Departure Warning
        // ----------------------------------------------------
        $display("TEST 3: Lane Departure Warning");
        sw_brake_arm = 1;
        @(negedge clk);
        lane_detected = 1;
        lane_severity = 2'b11; // Critical severity
        repeat(5) @(negedge clk);
        if (warning_lane && brake_authorized) $display("PASS: Lane warning triggered and brake applied.");
        lane_detected = 0;

        rst_n = 0;
        repeat(3) @(negedge clk);
        rst_n = 1;
        sw_brake_arm = 1;
        
        // ----------------------------------------------------
        // TEST 4: Speed Sign Overspeed
        // ----------------------------------------------------
        $display("TEST 4: Speed Sign Overspeed");
        @(negedge clk);
        sign_overspeed = 1;
        repeat(5) @(negedge clk);
        if (warning_sign) $display("PASS: Sign warning triggered.");
        sign_overspeed = 0;

        // ----------------------------------------------------
        // TEST 5: Watchdog System Fault
        // ----------------------------------------------------
        $display("TEST 5: Watchdog System Fault");
        @(negedge clk);
        stop_petting = 1; // STOP PETTING THE WATCHDOG
        
        // Wait for watchdog to expire (50 cycles)
        repeat(60) @(negedge clk);
        if (system_fault) $display("PASS: System fault triggered.");
        else $display("FAIL: Watchdog did not fault.");
        
        // Try to trigger an emergency while fault is active
        @(negedge clk);
        lane_detected = 1;
        lane_severity = 2'b11; 
        repeat(5) @(negedge clk);
        if (!brake_authorized) $display("PASS: Brake correctly blocked due to system fault safe-state!");
        else $display("FAIL: Brake authorized during fault!");

        repeat(10) @(negedge clk);
        $finish;
    end

    // Background Watchdog Petting 
    always begin
        #50;
        if (!stop_petting && !system_fault) wdt_pet = ~wdt_pet;
    end

endmodule

verification/tb/adas_features.vcd
$date
   Mon Sep 14 00:49:58 2026
$end

$version
  2025.1.0
  $dumpfile ("adas_features.vcd") 
$end

$timescale
  1ps
$end

$scope module tb_adas_features $end
$var reg 1 ! clk $end
$var reg 1 " rst_n $end
$var reg 1 # ped_detected $end
$var reg 1 $ obs_detected $end
$var reg 1 % lane_detected $end
$var reg 1 & sign_overspeed $end
$var reg 2 ' lane_severity [1:0] $end
$var reg 1 ( ped_en $end
$var reg 1 ) obs_en $end
$var reg 1 * lane_en $end
$var reg 1 + wdt_pet $end
$var reg 1 , stop_petting $end
$var reg 1 - sw_brake_arm $end
$var wire 1 . emergency_trigger $end
$var wire 1 / warning_ped $end
$var wire 1 0 warning_lane $end
$var wire 1 1 warning_sign $end
$var wire 1 2 system_fault $end
$var wire 1 3 brake_authorized $end
$scope module u_fusion $end
$var wire 1 4 clk $end
$var wire 1 5 rst_n $end
$var wire 1 6 ped_detected $end
$var wire 1 7 obs_detected $end
$var wire 1 8 lane_detected $end
$var wire 1 9 sign_overspeed $end
$var wire 2 : lane_severity [1:0] $end
$var wire 1 ; ped_en $end
$var wire 1 < obs_en $end
$var wire 1 = lane_en $end
$var reg 1 > emergency_trigger $end
$var reg 1 ? warning_ped $end
$var reg 1 @ warning_lane $end
$var reg 1 A warning_sign $end
$var wire 3 B hazard_score [2:0] $end
$upscope $end
$scope module u_safety $end
$var wire 1 C clk $end
$var wire 1 D rst_n $end
$var wire 1 E wdt_pet $end
$var reg 1 F system_fault $end
$var reg 32 G wdt_counter [31:0] $end
$var reg 1 H last_wdt_pet $end
$upscope $end
$scope module u_security $end
$var wire 1 I clk $end
$var wire 1 J rst_n $end
$var wire 1 K sw_brake_arm $end
$var wire 1 . emergency_trigger $end
$var wire 1 2 system_fault $end
$var reg 1 L brake_authorized $end
$var reg 2 M current_state [1:0] $end
$var reg 2 N next_state [1:0] $end
$upscope $end
$upscope $end
$enddefinitions $end

#0
$dumpvars
0!
0"
0#
0$
0%
0&
b0 '
1(
1)
1*
0+
0,
0-
0.
0/
00
01
02
03
04
05
06
07
08
09
b0 :
1;
1<
1=
0>
0?
0@
0A
b0 B
0C
0D
0E
0F
b0 G
0H
0I
0J
0K
0L
b0 M
b0 N
$end

#4000
1!
14
1C
1I

#8000
0!
04
0C
0I

#12000
1!
14
1C
1I

#16000
0!
04
0C
0I

#20000
1!
1"
14
15
1C
1D
b1 G
1I
1J

#24000
0!
04
0C
0I

#28000
1!
14
1C
b10 G
1I

#32000
0!
04
0C
0I

#36000
1!
14
1C
b11 G
1I

#40000
0!
1-
04
0C
0I
1K
b1 N

#44000
1!
14
1C
b100 G
1I
b1 M

#48000
0!
04
0C
0I

#50000
1+
1E

#52000
1!
14
1C
b0 G
1H
1I

#56000
0!
04
0C
0I

#60000
1!
1#
1.
1/
14
16
1>
1?
b100 B
1C
b1 G
1I
b10 N

#64000
0!
04
0C
0I

#68000
1!
13
14
1C
b10 G
1I
1L
b10 M

#72000
0!
04
0C
0I

#76000
1!
14
1C
b11 G
1I

#80000
0!
04
0C
0I

#84000
1!
14
1C
b100 G
1I

#88000
0!
04
0C
0I

#92000
1!
14
1C
b101 G
1I

#96000
0!
04
0C
0I

#100000
1!
0#
1%
b11 '
0+
0-
0/
10
03
14
06
18
b11 :
0?
1@
b11 B
1C
0E
b0 G
0H
1I
0K
0L
b0 M
b0 N

#104000
0!
04
0C
0I

#108000
1!
14
1C
b1 G
1I

#112000
0!
04
0C
0I

#116000
1!
14
1C
b10 G
1I

#120000
0!
04
0C
0I

#124000
1!
14
1C
b11 G
1I

#128000
0!
04
0C
0I

#132000
1!
14
1C
b100 G
1I

#136000
0!
04
0C
0I

#140000
1!
0"
0%
b0 '
0.
00
14
05
08
b0 :
0>
0@
b0 B
1C
0D
b0 G
1I
0J

#144000
0!
04
0C
0I

#148000
1!
14
1C
1I

#150000
1+
1E

#152000
0!
04
0C
0I

#156000
1!
14
1C
1I

#160000
0!
1"
1%
b11 '
1-
04
15
18
b11 :
b11 B
0C
1D
0I
1J
1K
b1 N

#164000
1!
1.
10
14
1>
1@
1C
1H
1I
b1 M
b10 N

#168000
0!
04
0C
0I

#172000
1!
13
14
1C
b1 G
1I
1L
b10 M

#176000
0!
04
0C
0I

#180000
1!
14
1C
b10 G
1I

#184000
0!
04
0C
0I

#188000
1!
14
1C
b11 G
1I

#192000
0!
04
0C
0I

#196000
1!
14
1C
b100 G
1I

#200000
0!
0"
0%
0+
0.
00
03
04
05
08
0>
0@
b0 B
0C
0D
0E
b0 G
0H
0I
0J
0L
b0 M
b1 N

#204000
1!
14
1C
1I

#208000
0!
04
0C
0I

#212000
1!
14
1C
1I

#216000
0!
04
0C
0I

#220000
1!
1"
1&
11
14
15
19
1A
b1 B
1C
1D
b1 G
1I
1J
b1 M

#224000
0!
04
0C
0I

#228000
1!
14
1C
b10 G
1I

#232000
0!
04
0C
0I

#236000
1!
14
1C
b11 G
1I

#240000
0!
04
0C
0I

#244000
1!
14
1C
b100 G
1I

#248000
0!
04
0C
0I

#250000
1+
1E

#252000
1!
14
1C
b0 G
1H
1I

#256000
0!
04
0C
0I

#260000
1!
0&
1,
01
14
09
0A
b0 B
1C
b1 G
1I

#264000
0!
04
0C
0I

#268000
1!
14
1C
b10 G
1I

#272000
0!
04
0C
0I

#276000
1!
14
1C
b11 G
1I

#280000
0!
04
0C
0I

#284000
1!
14
1C
b100 G
1I

#288000
0!
04
0C
0I

#292000
1!
14
1C
b101 G
1I

#296000
0!
04
0C
0I

#300000
1!
14
1C
b110 G
1I

#304000
0!
04
0C
0I

#308000
1!
14
1C
b111 G
1I

#312000
0!
04
0C
0I

#316000
1!
14
1C
b1000 G
1I

#320000
0!
04
0C
0I

#324000
1!
14
1C
b1001 G
1I

#328000
0!
04
0C
0I

#332000
1!
14
1C
b1010 G
1I

#336000
0!
04
0C
0I

#340000
1!
14
1C
b1011 G
1I

#344000
0!
04
0C
0I

#348000
1!
14
1C
b1100 G
1I

#352000
0!
04
0C
0I

#356000
1!
14
1C
b1101 G
1I

#360000
0!
04
0C
0I

#364000
1!
14
1C
b1110 G
1I

#368000
0!
04
0C
0I

#372000
1!
14
1C
b1111 G
1I

#376000
0!
04
0C
0I

#380000
1!
14
1C
b10000 G
1I

#384000
0!
04
0C
0I

#388000
1!
14
1C
b10001 G
1I

#392000
0!
04
0C
0I

#396000
1!
14
1C
b10010 G
1I

#400000
0!
04
0C
0I

#404000
1!
14
1C
b10011 G
1I

#408000
0!
04
0C
0I

#412000
1!
14
1C
b10100 G
1I

#416000
0!
04
0C
0I

#420000
1!
14
1C
b10101 G
1I

#424000
0!
04
0C
0I

#428000
1!
14
1C
b10110 G
1I

#432000
0!
04
0C
0I

#436000
1!
14
1C
b10111 G
1I

#440000
0!
04
0C
0I

#444000
1!
14
1C
b11000 G
1I

#448000
0!
04
0C
0I

#452000
1!
14
1C
b11001 G
1I

#456000
0!
04
0C
0I

#460000
1!
14
1C
b11010 G
1I

#464000
0!
04
0C
0I

#468000
1!
14
1C
b11011 G
1I

#472000
0!
04
0C
0I

#476000
1!
14
1C
b11100 G
1I

#480000
0!
04
0C
0I

#484000
1!
14
1C
b11101 G
1I

#488000
0!
04
0C
0I

#492000
1!
14
1C
b11110 G
1I

#496000
0!
04
0C
0I

#500000
1!
14
1C
b11111 G
1I

#504000
0!
04
0C
0I

#508000
1!
14
1C
b100000 G
1I

#512000
0!
04
0C
0I

#516000
1!
14
1C
b100001 G
1I

#520000
0!
04
0C
0I

#524000
1!
14
1C
b100010 G
1I

#528000
0!
04
0C
0I

#532000
1!
14
1C
b100011 G
1I

#536000
0!
04
0C
0I

#540000
1!
14
1C
b100100 G
1I

#544000
0!
04
0C
0I

#548000
1!
14
1C
b100101 G
1I

#552000
0!
04
0C
0I

#556000
1!
14
1C
b100110 G
1I

#560000
0!
04
0C
0I

#564000
1!
14
1C
b100111 G
1I

#568000
0!
04
0C
0I

#572000
1!
14
1C
b101000 G
1I

#576000
0!
04
0C
0I

#580000
1!
14
1C
b101001 G
1I

#584000
0!
04
0C
0I

#588000
1!
14
1C
b101010 G
1I

#592000
0!
04
0C
0I

#596000
1!
14
1C
b101011 G
1I

#600000
0!
04
0C
0I

#604000
1!
14
1C
b101100 G
1I

#608000
0!
04
0C
0I

#612000
1!
14
1C
b101101 G
1I

#616000
0!
04
0C
0I

#620000
1!
14
1C
b101110 G
1I

#624000
0!
04
0C
0I

#628000
1!
14
1C
b101111 G
1I

#632000
0!
04
0C
0I

#636000
1!
14
1C
b110000 G
1I

#640000
0!
04
0C
0I

#644000
1!
14
1C
b110001 G
1I

#648000
0!
04
0C
0I

#652000
1!
14
1C
b110010 G
1I

#656000
0!
04
0C
0I

#660000
1!
12
14
1C
1F
b110011 G
1I

#664000
0!
04
0C
0I

#668000
1!
14
1C
1I
b11 M
b11 N

#672000
0!
04
0C
0I

#676000
1!
14
1C
1I

#680000
0!
04
0C
0I

#684000
1!
14
1C
1I

#688000
0!
04
0C
0I

#692000
1!
14
1C
1I

#696000
0!
04
0C
0I

#700000
1!
14
1C
1I

#704000
0!
04
0C
0I

#708000
1!
14
1C
1I

#712000
0!
04
0C
0I

#716000
1!
14
1C
1I

#720000
0!
04
0C
0I

#724000
1!
14
1C
1I

#728000
0!
04
0C
0I

#732000
1!
14
1C
1I

#736000
0!
04
0C
0I

#740000
1!
14
1C
1I

#744000
0!
04
0C
0I

#748000
1!
14
1C
1I

#752000
0!
04
0C
0I

#756000
1!
14
1C
1I

#760000
0!
1%
04
18
b11 B
0C
0I

#764000
1!
1.
10
14
1>
1@
1C
1I

